README
setup.py
dummy_pool.egg-info/PKG-INFO
dummy_pool.egg-info/SOURCES.txt
dummy_pool.egg-info/dependency_links.txt
dummy_pool.egg-info/not-zip-safe
dummy_pool.egg-info/top_level.txt
pool/__init__.py
pool/event.py
pool/events.py
pool/exc.py
pool/interfaces.py
pool/log.py
pool/pool.py
pool/util/__init__.py
pool/util/compat.py
pool/util/langhelpers.py
pool/util/queue.py