Metadata-Version: 1.0
Name: dummy-pool
Version: 0.0.26
Summary: pool
Home-page: UNKNOWN
Author: tonic
Author-email: tonic@wolege.ca
License: UNKNOWN
Platform: UNKNOWN
